Metadata-Version: 2.1
Name: tesseract2dict
Version: 1.3
Summary: Solution to extract the text from image and get wordlevel output as dataframe and also to extract text from given boundingBox
Home-page: https://github.com/Sreekiranar/tesseract2dict.git
Author-email: sreekiranar@gmail.com, anilprasadmn@gmail.com
License: MIT
Platform: UNKNOWN
